docs/README.md
docs/__init__.py
docs/autogen.py
docs/mathjaxhelper.js
docs/mkdocs.yml
docs/structure.py
docs/__pycache__/__init__.cpython-38.pyc
docs/__pycache__/structure.cpython-38.pyc
docs/sources/CNAME
docs/sources/constraints.md
docs/sources/contributing.md
docs/sources/examples.md
docs/sources/fields.md
docs/sources/functionals.md
docs/sources/index.md
docs/sources/scimodels.md
docs/sources/utils.md
docs/sources/variables.md
docs/sources/why-use-sciann.md
docs/sources/examples/curve-fitting-1d.md
docs/sources/examples/example-fitting-1d-lstm.md
docs/sources/examples/example-fitting-1d-rnn.md
docs/sources/examples/example-fitting-1d.md
docs/sources/examples/example-fitting-fourier.md
docs/sources/examples/test_diff.md
docs/sources/getting-started/functional-guide.md
docs/sources/getting-started/scimodel-guide.md
docs/templates/CNAME
docs/templates/constraints.md
docs/templates/examples.md
docs/templates/fields.md
docs/templates/functionals.md
docs/templates/index.md
docs/templates/scimodels.md
docs/templates/utils.md
docs/templates/variables.md
docs/templates/why-use-sciann.md
docs/templates/examples/curve-fitting-1d.md
docs/templates/getting-started/functional-guide.md
docs/templates/getting-started/scimodel-guide.md
docs/theme/404.html
docs/theme/base.html
docs/theme/breadcrumbs.html
docs/theme/footer.html
docs/theme/main.html
docs/theme/nav.html
docs/theme/search.html
docs/theme/searchbox.html
docs/theme/toc.html
docs/theme/versions.html
docs/theme/css/theme.css
docs/theme/css/theme_extra.css
docs/theme/js/jquery-2.1.1.min.js
docs/theme/js/modernizr-2.8.3.min.js
docs/theme/js/theme.js
sciann/__init__.py
sciann/constraints/__init__.py
sciann/constraints/constraint.py
sciann/constraints/data.py
sciann/constraints/minmax.py
sciann/constraints/pde.py
sciann/constraints/tie.py
sciann/functionals/__init__.py
sciann/functionals/field.py
sciann/functionals/functional.py
sciann/functionals/mlp_functional.py
sciann/functionals/parameter.py
SciANN-0.7.0.1.dist-info/LICENSE
SciANN-0.7.0.1.dist-info/METADATA
SciANN-0.7.0.1.dist-info/WHEEL
SciANN-0.7.0.1.dist-info/top_level.txt
SciANN-0.7.0.1.dist-info/RECORD
